{"display":{"thirdperson_righthand":{"rotation":[0,132,0],"translation":[0,2.5,0.5],"scale":[0.5,0.5,0.5]},"thirdperson_lefthand":{"rotation":[0,132,0],"translation":[0,2.5,0.5],"scale":[0.5,0.5,0.5]},"firstperson_righthand":{"rotation":[0,122,0],"translation":[3.75,-0.25,-6.25],"scale":[0.7,0.7,0.7]},"firstperson_lefthand":{"rotation":[0,122,0],"translation":[3.75,-0.25,-6.25],"scale":[0.7,0.7,0.7]},"ground":{"rotation":[90,0,0],"translation":[0,-2.25,1],"scale":[0.8,0.8,0.8]},"gui":{"rotation":[29,142,0],"translation":[-0.25,0.25,0],"scale":[0.8,0.8,0.8]},"fixed":{"translation":[0,3,-0.25],"scale":[2,2,2]}},"texture_size":[32,32],"textures":{"0":"./transmitter","particle":"./transmitter"},"elements":[{"from":[4,0,8],"to":[12,13,9],"rotation":{"angle":0,"axis":"y","origin":[10,0,7]},"faces":{"north":{"uv":[0,9.5,4,16],"texture":"#0"},"east":{"uv":[0,9.5,0.5,16],"texture":"#0"},"south":{"uv":[4.5,9.5,8.5,16],"texture":"#0"},"west":{"uv":[3.5,9.5,4,16],"texture":"#0"},"up":{"uv":[0,9.5,4,10],"texture":"#0"},"down":{"uv":[0,15.5,4,16],"texture":"#0"}}}]}